vietfin/__init__.py
vietfin/abstract/__init__.py
vietfin/abstract/data.py
vietfin/abstract/factory.py
vietfin/abstract/interface.py
vietfin/abstract/vfobject.py
vietfin/components/__init__.py
vietfin/components/derivatives.py
vietfin/components/equity.py
vietfin/components/equity_calendar.py
vietfin/components/equity_discovery.py
vietfin/components/equity_fundamental.py
vietfin/components/equity_ownership.py
vietfin/components/equity_price.py
vietfin/components/etf.py
vietfin/components/funds.py
vietfin/components/index.py
vietfin/components/news.py
vietfin/providers/__init__.py
vietfin/providers/cafef/__init__.py
vietfin/providers/cafef/models/__init__.py
vietfin/providers/cafef/models/equity_ownership_foreign.py
vietfin/providers/cafef/models/equity_ownership_prop.py
vietfin/providers/cafef/provider.py
vietfin/providers/cafef/utils/equity_ownership_foreign.py
vietfin/providers/cafef/utils/equity_ownership_prop.py
vietfin/providers/cafef/utils/helpers.py
vietfin/providers/dnse/__init__.py
vietfin/providers/dnse/models/__init__.py
vietfin/providers/dnse/models/equity_price_historical.py
vietfin/providers/dnse/provider.py
vietfin/providers/dnse/utils/__init__.py
vietfin/providers/dnse/utils/equity_price_historical.py
vietfin/providers/dnse/utils/helpers.py
vietfin/providers/fmarket/__init__.py
vietfin/providers/fmarket/models/__init__.py
vietfin/providers/fmarket/models/fund_asset_types.py
vietfin/providers/fmarket/models/fund_historical_nav.py
vietfin/providers/fmarket/models/fund_historical_nav_performance.py
vietfin/providers/fmarket/models/fund_holdings.py
vietfin/providers/fmarket/models/fund_industries.py
vietfin/providers/fmarket/models/fund_search.py
vietfin/providers/fmarket/provider.py
vietfin/providers/fmarket/py.typed
vietfin/providers/fmarket/utils/__init__.py
vietfin/providers/fmarket/utils/funds_historical.py
vietfin/providers/fmarket/utils/funds_holdings.py
vietfin/providers/fmarket/utils/funds_search.py
vietfin/providers/fmarket/utils/helpers.py
vietfin-0.2.0.dist-info/LICENSE
vietfin-0.2.0.dist-info/METADATA
vietfin-0.2.0.dist-info/WHEEL
vietfin-0.2.0.dist-info/RECORD
