Metadata-Version: 2.1
Name: vietfin
Version: 0.2.0
Summary: Python package to fetch Vietnam stock market data
Home-page: https://github.com/vietfin/vietfin
License: Apache-2.0
Keywords: vietnam,stock,market,data,finance,etf,investment,funds
Author: Huy
Author-email: vietfin.numbness179@simplelogin.fr
Requires-Python: >=3.10,<4.0
Classifier: Development Status :: 3 - Alpha
Classifier: Intended Audience :: Developers
Classifier: Intended Audience :: Science/Research
Classifier: License :: OSI Approved :: Apache Software License
Classifier: Programming Language :: Python :: 3
Classifier: Programming Language :: Python :: 3.10
Classifier: Programming Language :: Python :: 3.11
Classifier: Programming Language :: Python :: 3.12
Classifier: Topic :: Office/Business :: Financial :: Investment
Classifier: Topic :: Scientific/Engineering
Classifier: Topic :: Software Development :: Libraries :: Python Modules
Classifier: Typing :: Typed
Requires-Dist: httpx (>=0.27.0,<0.28.0)
Requires-Dist: openpyxl (>=3.1.2,<4.0.0)
Requires-Dist: pandas (>=2.1.4,<3.0.0)
Requires-Dist: pydantic (>=2.5.3,<3.0.0)
Requires-Dist: selectolax (>=0.3.21,<0.4.0)
Project-URL: Documentation, https://github.com/vietfin/vietfin
Project-URL: Repository, https://github.com/vietfin/vietfin
